pyCftool/__init__.py
pyCftool/cftooloptions.ui
pyCftool/export.py
pyCftool/loadgui.py
pyCftool/mplwidget.py
pyCftool/options.py
pyCftool/pyCftool.py
pyCftool/pycftoolGUI.ui
pyCftool-1.0.0.dist-info/LICENSE.txt
pyCftool-1.0.0.dist-info/METADATA
pyCftool-1.0.0.dist-info/WHEEL
pyCftool-1.0.0.dist-info/top_level.txt
pyCftool-1.0.0.dist-info/RECORD
