Metadata-Version: 2.1
Name: pyCftool
Version: 1.0.0
Summary: Interactive python fitting interface
Author: Andreas Forum (TehForum)
Author-email: <andforum@hotmail.com>
Keywords: python,fit,statistics,modelling,science
Classifier: Development Status :: 5 - Production/Stable
Classifier: Intended Audience :: Science/Research
Classifier: Programming Language :: Python :: 3.6
Classifier: Operating System :: Unix
Classifier: Operating System :: MacOS :: MacOS X
Classifier: Operating System :: Microsoft :: Windows
License-File: LICENSE.txt
Requires-Dist: PySide6
Requires-Dist: numpy
Requires-Dist: scipy
Requires-Dist: matplotlib
